{
  "failed_count": 41,
  "failed_runs": [
    {
      "branch": "main",
      "commit": "1ee1cb23e2e67e684e01a833181e97a635e6717b",
      "conclusion": "failure",
      "created_at": "2026-07-23T12:51:24Z",
      "html_url": "https://github.com/psw2025-cmd/Genesis_System3/actions/runs/30008700158",
      "run_id": 30008700158,
      "updated_at": "2026-07-23T12:52:17Z",
      "workflow": "Dashboard Visible Proof Warmed"
    },
    {
      "branch": "main",
      "commit": "1ee1cb23e2e67e684e01a833181e97a635e6717b",
      "conclusion": "failure",
      "created_at": "2026-07-23T12:50:18Z",
      "html_url": "https://github.com/psw2025-cmd/Genesis_System3/actions/runs/30008623016",
      "run_id": 30008623016,
      "updated_at": "2026-07-23T12:50:51Z",
      "workflow": "System3 Backend Live Simulation Proof"
    },
    {
      "branch": "main",
      "commit": "1ee1cb23e2e67e684e01a833181e97a635e6717b",
      "conclusion": "failure",
      "created_at": "2026-07-23T12:49:14Z",
      "html_url": "https://github.com/psw2025-cmd/Genesis_System3/actions/runs/30008545719",
      "run_id": 30008545719,
      "updated_at": "2026-07-23T12:49:26Z",
      "workflow": "Dashboard Visual Proof Strict Gate"
    },
    {
      "branch": "main",
      "commit": "249cd62069353406af8d0f1a1599ea6065afcac9",
      "conclusion": "failure",
      "created_at": "2026-07-23T12:48:17Z",
      "html_url": "https://github.com/psw2025-cmd/Genesis_System3/actions/runs/30008480322",
      "run_id": 30008480322,
      "updated_at": "2026-07-23T12:48:50Z",
      "workflow": "Dashboard Deploy Provenance Gate"
    },
    {
      "branch": "main",
      "commit": "249cd62069353406af8d0f1a1599ea6065afcac9",
      "conclusion": "failure",
      "created_at": "2026-07-23T12:47:02Z",
      "html_url": "https://github.com/psw2025-cmd/Genesis_System3/actions/runs/30008392059",
      "run_id": 30008392059,
      "updated_at": "2026-07-23T12:52:41Z",
      "workflow": "System3 Windows Self-Hosted Full Proof"
    },
    {
      "branch": "main",
      "commit": "249cd62069353406af8d0f1a1599ea6065afcac9",
      "conclusion": "failure",
      "created_at": "2026-07-23T12:46:56Z",
      "html_url": "https://github.com/psw2025-cmd/Genesis_System3/actions/runs/30008384947",
      "run_id": 30008384947,
      "updated_at": "2026-07-23T12:53:11Z",
      "workflow": "Dashboard Visible Settle Proof"
    },
    {
      "branch": "main",
      "commit": "e1bfd0b2bf50a599c7d3b4bbc37a8f322d298008",
      "conclusion": "failure",
      "created_at": "2026-07-23T12:35:14Z",
      "html_url": "https://github.com/psw2025-cmd/Genesis_System3/actions/runs/30007579694",
      "run_id": 30007579694,
      "updated_at": "2026-07-23T12:35:25Z",
      "workflow": "Dashboard Visual Proof Strict Gate"
    },
    {
      "branch": "main",
      "commit": "e1bfd0b2bf50a599c7d3b4bbc37a8f322d298008",
      "conclusion": "failure",
      "created_at": "2026-07-23T12:35:14Z",
      "html_url": "https://github.com/psw2025-cmd/Genesis_System3/actions/runs/30007579685",
      "run_id": 30007579685,
      "updated_at": "2026-07-23T12:43:38Z",
      "workflow": "System3 Safe Repair Runner"
    },
    {
      "branch": "main",
      "commit": "e1bfd0b2bf50a599c7d3b4bbc37a8f322d298008",
      "conclusion": "failure",
      "created_at": "2026-07-23T12:35:14Z",
      "html_url": "https://github.com/psw2025-cmd/Genesis_System3/actions/runs/30007579671",
      "run_id": 30007579671,
      "updated_at": "2026-07-23T12:35:24Z",
      "workflow": "Dashboard Visual Loading Postflight"
    },
    {
      "branch": "main",
      "commit": "e1bfd0b2bf50a599c7d3b4bbc37a8f322d298008",
      "conclusion": "failure",
      "created_at": "2026-07-23T12:35:14Z",
      "html_url": "https://github.com/psw2025-cmd/Genesis_System3/actions/runs/30007579665",
      "run_id": 30007579665,
      "updated_at": "2026-07-23T12:35:35Z",
      "workflow": "System3 Secure Install Credential Audit"
    },
    {
      "branch": "main",
      "commit": "e1bfd0b2bf50a599c7d3b4bbc37a8f322d298008",
      "conclusion": "failure",
      "created_at": "2026-07-23T12:35:14Z",
      "html_url": "https://github.com/psw2025-cmd/Genesis_System3/actions/runs/30007579651",
      "run_id": 30007579651,
      "updated_at": "2026-07-23T12:38:28Z",
      "workflow": "Dashboard Shell Diagnostic"
    },
    {
      "branch": "main",
      "commit": "e1bfd0b2bf50a599c7d3b4bbc37a8f322d298008",
      "conclusion": "failure",
      "created_at": "2026-07-23T12:35:14Z",
      "html_url": "https://github.com/psw2025-cmd/Genesis_System3/actions/runs/30007579600",
      "run_id": 30007579600,
      "updated_at": "2026-07-23T12:35:27Z",
      "workflow": "System3 Experimental Solution Planner"
    },
    {
      "branch": "main",
      "commit": "e1bfd0b2bf50a599c7d3b4bbc37a8f322d298008",
      "conclusion": "cancelled",
      "created_at": "2026-07-23T12:35:11Z",
      "html_url": "https://github.com/psw2025-cmd/Genesis_System3/actions/runs/30007576203",
      "run_id": 30007576203,
      "updated_at": "2026-07-23T12:35:25Z",
      "workflow": "System3 Safe Repair Runner"
    },
    {
      "branch": "main",
      "commit": "e1bfd0b2bf50a599c7d3b4bbc37a8f322d298008",
      "conclusion": "failure",
      "created_at": "2026-07-23T12:35:11Z",
      "html_url": "https://github.com/psw2025-cmd/Genesis_System3/actions/runs/30007576044",
      "run_id": 30007576044,
      "updated_at": "2026-07-23T12:55:46Z",
      "workflow": "Dashboard Visible Issue Tracker"
    },
    {
      "branch": "main",
      "commit": "e1bfd0b2bf50a599c7d3b4bbc37a8f322d298008",
      "conclusion": "failure",
      "created_at": "2026-07-23T12:35:11Z",
      "html_url": "https://github.com/psw2025-cmd/Genesis_System3/actions/runs/30007576041",
      "run_id": 30007576041,
      "updated_at": "2026-07-23T12:35:22Z",
      "workflow": "System3 Experimental Solution Planner"
    },
    {
      "branch": "main",
      "commit": "9f804a41978e983d3b8f074d8d7b49285ad9905a",
      "conclusion": "cancelled",
      "created_at": "2026-07-23T12:34:47Z",
      "html_url": "https://github.com/psw2025-cmd/Genesis_System3/actions/runs/30007549654",
      "run_id": 30007549654,
      "updated_at": "2026-07-23T12:35:14Z",
      "workflow": "System3 Safe Repair Runner"
    },
    {
      "branch": "main",
      "commit": "9f804a41978e983d3b8f074d8d7b49285ad9905a",
      "conclusion": "failure",
      "created_at": "2026-07-23T12:34:47Z",
      "html_url": "https://github.com/psw2025-cmd/Genesis_System3/actions/runs/30007549633",
      "run_id": 30007549633,
      "updated_at": "2026-07-23T12:35:00Z",
      "workflow": "System3 Experimental Solution Planner"
    },
    {
      "branch": "main",
      "commit": "9f804a41978e983d3b8f074d8d7b49285ad9905a",
      "conclusion": "cancelled",
      "created_at": "2026-07-23T12:34:47Z",
      "html_url": "https://github.com/psw2025-cmd/Genesis_System3/actions/runs/30007549566",
      "run_id": 30007549566,
      "updated_at": "2026-07-23T12:35:12Z",
      "workflow": "Dashboard Visible Issue Tracker"
    },
    {
      "branch": "main",
      "commit": "9f804a41978e983d3b8f074d8d7b49285ad9905a",
      "conclusion": "failure",
      "created_at": "2026-07-23T12:34:19Z",
      "html_url": "https://github.com/psw2025-cmd/Genesis_System3/actions/runs/30007518162",
      "run_id": 30007518162,
      "updated_at": "2026-07-23T12:35:37Z",
      "workflow": "System3 Autopilot Proof Board"
    },
    {
      "branch": "main",
      "commit": "8a958295d207e31ed8a3511649ddf20e3e572586",
      "conclusion": "failure",
      "created_at": "2026-07-23T12:33:58Z",
      "html_url": "https://github.com/psw2025-cmd/Genesis_System3/actions/runs/30007495053",
      "run_id": 30007495053,
      "updated_at": "2026-07-23T12:34:16Z",
      "workflow": "System3 Secure Install Credential Audit"
    },
    {
      "branch": "main",
      "commit": "8a958295d207e31ed8a3511649ddf20e3e572586",
      "conclusion": "failure",
      "created_at": "2026-07-23T12:33:58Z",
      "html_url": "https://github.com/psw2025-cmd/Genesis_System3/actions/runs/30007494981",
      "run_id": 30007494981,
      "updated_at": "2026-07-23T12:34:09Z",
      "workflow": "System3 Experimental Solution Planner"
    },
    {
      "branch": "main",
      "commit": "8a958295d207e31ed8a3511649ddf20e3e572586",
      "conclusion": "failure",
      "created_at": "2026-07-23T12:33:58Z",
      "html_url": "https://github.com/psw2025-cmd/Genesis_System3/actions/runs/30007494974",
      "run_id": 30007494974,
      "updated_at": "2026-07-23T12:35:08Z",
      "workflow": "System3 Autopilot Proof Board"
    },
    {
      "branch": "main",
      "commit": "28d15711e70c71caada6185ebacf01a73d770815",
      "conclusion": "failure",
      "created_at": "2026-07-23T12:33:35Z",
      "html_url": "https://github.com/psw2025-cmd/Genesis_System3/actions/runs/30007469496",
      "run_id": 30007469496,
      "updated_at": "2026-07-23T12:34:44Z",
      "workflow": "System3 Autopilot Proof Board"
    },
    {
      "branch": "main",
      "commit": "28d15711e70c71caada6185ebacf01a73d770815",
      "conclusion": "cancelled",
      "created_at": "2026-07-23T12:33:35Z",
      "html_url": "https://github.com/psw2025-cmd/Genesis_System3/actions/runs/30007469384",
      "run_id": 30007469384,
      "updated_at": "2026-07-23T12:35:03Z",
      "workflow": "System3 Safe Repair Runner"
    },
    {
      "branch": "main",
      "commit": "68e57caf7fb93da632626113bc7a8cccf0f527b2",
      "conclusion": "failure",
      "created_at": "2026-07-23T12:33:14Z",
      "html_url": "https://github.com/psw2025-cmd/Genesis_System3/actions/runs/30007446466",
      "run_id": 30007446466,
      "updated_at": "2026-07-23T12:33:33Z",
      "workflow": "System3 GitHub Render Failure Tracker"
    },
    {
      "branch": "main",
      "commit": "d6664adecaa52fb28271a8054603301f2d7aaab9",
      "conclusion": "cancelled",
      "created_at": "2026-07-23T12:27:43Z",
      "html_url": "https://github.com/psw2025-cmd/Genesis_System3/actions/runs/30007073427",
      "run_id": 30007073427,
      "updated_at": "2026-07-23T12:34:10Z",
      "workflow": "System3 Safe Repair Runner"
    },
    {
      "branch": "main",
      "commit": "35c0d2d36aa5c588fa8ded0b21c306ee90f2e6f7",
      "conclusion": "failure",
      "created_at": "2026-07-23T12:25:58Z",
      "html_url": "https://github.com/psw2025-cmd/Genesis_System3/actions/runs/30006956073",
      "run_id": 30006956073,
      "updated_at": "2026-07-23T12:26:07Z",
      "workflow": "System3 Experimental Solution Planner"
    },
    {
      "branch": "main",
      "commit": "35c0d2d36aa5c588fa8ded0b21c306ee90f2e6f7",
      "conclusion": "cancelled",
      "created_at": "2026-07-23T12:25:58Z",
      "html_url": "https://github.com/psw2025-cmd/Genesis_System3/actions/runs/30006956035",
      "run_id": 30006956035,
      "updated_at": "2026-07-23T12:28:18Z",
      "workflow": "System3 Safe Repair Runner"
    },
    {
      "branch": "main",
      "commit": "cc5f4116a0a7aed36ae74e28d82dd94ea85e148d",
      "conclusion": "failure",
      "created_at": "2026-07-23T12:25:21Z",
      "html_url": "https://github.com/psw2025-cmd/Genesis_System3/actions/runs/30006915603",
      "run_id": 30006915603,
      "updated_at": "2026-07-23T12:25:31Z",
      "workflow": "System3 Experimental Solution Planner"
    },
    {
      "branch": "main",
      "commit": "cc5f4116a0a7aed36ae74e28d82dd94ea85e148d",
      "conclusion": "failure",
      "created_at": "2026-07-23T12:25:21Z",
      "html_url": "https://github.com/psw2025-cmd/Genesis_System3/actions/runs/30006915483",
      "run_id": 30006915483,
      "updated_at": "2026-07-23T12:26:24Z",
      "workflow": "System3 Autopilot Proof Board"
    },
    {
      "branch": "main",
      "commit": "cc5f4116a0a7aed36ae74e28d82dd94ea85e148d",
      "conclusion": "failure",
      "created_at": "2026-07-23T12:25:20Z",
      "html_url": "https://github.com/psw2025-cmd/Genesis_System3/actions/runs/30006915380",
      "run_id": 30006915380,
      "updated_at": "2026-07-23T12:25:46Z",
      "workflow": "System3 Secure Install Credential Audit"
    },
    {
      "branch": "main",
      "commit": "cc5f4116a0a7aed36ae74e28d82dd94ea85e148d",
      "conclusion": "failure",
      "created_at": "2026-07-23T12:25:18Z",
      "html_url": "https://github.com/psw2025-cmd/Genesis_System3/actions/runs/30006912315",
      "run_id": 30006912315,
      "updated_at": "2026-07-23T12:26:28Z",
      "workflow": "System3 Autopilot Proof Board"
    },
    {
      "branch": "main",
      "commit": "75325f8f2b0cd49b53c6bf882ad43793f60360fc",
      "conclusion": "failure",
      "created_at": "2026-07-23T12:25:04Z",
      "html_url": "https://github.com/psw2025-cmd/Genesis_System3/actions/runs/30006896468",
      "run_id": 30006896468,
      "updated_at": "2026-07-23T12:25:13Z",
      "workflow": "System3 Experimental Solution Planner"
    },
    {
      "branch": "main",
      "commit": "75325f8f2b0cd49b53c6bf882ad43793f60360fc",
      "conclusion": "cancelled",
      "created_at": "2026-07-23T12:25:04Z",
      "html_url": "https://github.com/psw2025-cmd/Genesis_System3/actions/runs/30006896391",
      "run_id": 30006896391,
      "updated_at": "2026-07-23T12:26:15Z",
      "workflow": "System3 Safe Repair Runner"
    },
    {
      "branch": "main",
      "commit": "75325f8f2b0cd49b53c6bf882ad43793f60360fc",
      "conclusion": "failure",
      "created_at": "2026-07-23T12:25:04Z",
      "html_url": "https://github.com/psw2025-cmd/Genesis_System3/actions/runs/30006896363",
      "run_id": 30006896363,
      "updated_at": "2026-07-23T12:43:33Z",
      "workflow": "Dashboard Visible Issue Tracker"
    },
    {
      "branch": "main",
      "commit": "75325f8f2b0cd49b53c6bf882ad43793f60360fc",
      "conclusion": "failure",
      "created_at": "2026-07-23T12:24:58Z",
      "html_url": "https://github.com/psw2025-cmd/Genesis_System3/actions/runs/30006889662",
      "run_id": 30006889662,
      "updated_at": "2026-07-23T12:28:19Z",
      "workflow": "Dashboard Shell Diagnostic"
    },
    {
      "branch": "main",
      "commit": "75325f8f2b0cd49b53c6bf882ad43793f60360fc",
      "conclusion": "cancelled",
      "created_at": "2026-07-23T12:24:58Z",
      "html_url": "https://github.com/psw2025-cmd/Genesis_System3/actions/runs/30006889556",
      "run_id": 30006889556,
      "updated_at": "2026-07-23T12:25:05Z",
      "workflow": "System3 Safe Repair Runner"
    },
    {
      "branch": "main",
      "commit": "75325f8f2b0cd49b53c6bf882ad43793f60360fc",
      "conclusion": "failure",
      "created_at": "2026-07-23T12:24:58Z",
      "html_url": "https://github.com/psw2025-cmd/Genesis_System3/actions/runs/30006889547",
      "run_id": 30006889547,
      "updated_at": "2026-07-23T12:25:55Z",
      "workflow": "System3 Autopilot Proof Board"
    },
    {
      "branch": "main",
      "commit": "75325f8f2b0cd49b53c6bf882ad43793f60360fc",
      "conclusion": "failure",
      "created_at": "2026-07-23T12:24:58Z",
      "html_url": "https://github.com/psw2025-cmd/Genesis_System3/actions/runs/30006889539",
      "run_id": 30006889539,
      "updated_at": "2026-07-23T12:25:16Z",
      "workflow": "System3 Secure Install Credential Audit"
    },
    {
      "branch": "main",
      "commit": "75325f8f2b0cd49b53c6bf882ad43793f60360fc",
      "conclusion": "failure",
      "created_at": "2026-07-23T12:24:58Z",
      "html_url": "https://github.com/psw2025-cmd/Genesis_System3/actions/runs/30006889538",
      "run_id": 30006889538,
      "updated_at": "2026-07-23T12:25:09Z",
      "workflow": "Dashboard Visual Proof Strict Gate"
    },
    {
      "branch": "main",
      "commit": "75325f8f2b0cd49b53c6bf882ad43793f60360fc",
      "conclusion": "failure",
      "created_at": "2026-07-23T12:24:58Z",
      "html_url": "https://github.com/psw2025-cmd/Genesis_System3/actions/runs/30006889536",
      "run_id": 30006889536,
      "updated_at": "2026-07-23T12:25:07Z",
      "workflow": "Dashboard Visual Loading Postflight"
    }
  ],
  "generated_utc": "2026-07-23T13:01:18.870188+00:00",
  "note": "Workflow failure tracker. Failed workflows remain TODO until a later successful run is proven.",
  "repository": "psw2025-cmd/Genesis_System3",
  "status": "BLOCKED",
  "todo": [
    "Fix workflow 'Dashboard Visible Proof Warmed' run 30008700158 conclusion=failure commit=1ee1cb23e2e67e684e01a833181e97a635e6717b",
    "Fix workflow 'System3 Backend Live Simulation Proof' run 30008623016 conclusion=failure commit=1ee1cb23e2e67e684e01a833181e97a635e6717b",
    "Fix workflow 'Dashboard Visual Proof Strict Gate' run 30008545719 conclusion=failure commit=1ee1cb23e2e67e684e01a833181e97a635e6717b",
    "Fix workflow 'Dashboard Deploy Provenance Gate' run 30008480322 conclusion=failure commit=249cd62069353406af8d0f1a1599ea6065afcac9",
    "Fix workflow 'System3 Windows Self-Hosted Full Proof' run 30008392059 conclusion=failure commit=249cd62069353406af8d0f1a1599ea6065afcac9",
    "Fix workflow 'Dashboard Visible Settle Proof' run 30008384947 conclusion=failure commit=249cd62069353406af8d0f1a1599ea6065afcac9",
    "Fix workflow 'Dashboard Visual Proof Strict Gate' run 30007579694 conclusion=failure commit=e1bfd0b2bf50a599c7d3b4bbc37a8f322d298008",
    "Fix workflow 'System3 Safe Repair Runner' run 30007579685 conclusion=failure commit=e1bfd0b2bf50a599c7d3b4bbc37a8f322d298008",
    "Fix workflow 'Dashboard Visual Loading Postflight' run 30007579671 conclusion=failure commit=e1bfd0b2bf50a599c7d3b4bbc37a8f322d298008",
    "Fix workflow 'System3 Secure Install Credential Audit' run 30007579665 conclusion=failure commit=e1bfd0b2bf50a599c7d3b4bbc37a8f322d298008",
    "Fix workflow 'Dashboard Shell Diagnostic' run 30007579651 conclusion=failure commit=e1bfd0b2bf50a599c7d3b4bbc37a8f322d298008",
    "Fix workflow 'System3 Experimental Solution Planner' run 30007579600 conclusion=failure commit=e1bfd0b2bf50a599c7d3b4bbc37a8f322d298008",
    "Fix workflow 'System3 Safe Repair Runner' run 30007576203 conclusion=cancelled commit=e1bfd0b2bf50a599c7d3b4bbc37a8f322d298008",
    "Fix workflow 'Dashboard Visible Issue Tracker' run 30007576044 conclusion=failure commit=e1bfd0b2bf50a599c7d3b4bbc37a8f322d298008",
    "Fix workflow 'System3 Experimental Solution Planner' run 30007576041 conclusion=failure commit=e1bfd0b2bf50a599c7d3b4bbc37a8f322d298008",
    "Fix workflow 'System3 Safe Repair Runner' run 30007549654 conclusion=cancelled commit=9f804a41978e983d3b8f074d8d7b49285ad9905a",
    "Fix workflow 'System3 Experimental Solution Planner' run 30007549633 conclusion=failure commit=9f804a41978e983d3b8f074d8d7b49285ad9905a",
    "Fix workflow 'Dashboard Visible Issue Tracker' run 30007549566 conclusion=cancelled commit=9f804a41978e983d3b8f074d8d7b49285ad9905a",
    "Fix workflow 'System3 Autopilot Proof Board' run 30007518162 conclusion=failure commit=9f804a41978e983d3b8f074d8d7b49285ad9905a",
    "Fix workflow 'System3 Secure Install Credential Audit' run 30007495053 conclusion=failure commit=8a958295d207e31ed8a3511649ddf20e3e572586",
    "Fix workflow 'System3 Experimental Solution Planner' run 30007494981 conclusion=failure commit=8a958295d207e31ed8a3511649ddf20e3e572586",
    "Fix workflow 'System3 Autopilot Proof Board' run 30007494974 conclusion=failure commit=8a958295d207e31ed8a3511649ddf20e3e572586",
    "Fix workflow 'System3 Autopilot Proof Board' run 30007469496 conclusion=failure commit=28d15711e70c71caada6185ebacf01a73d770815",
    "Fix workflow 'System3 Safe Repair Runner' run 30007469384 conclusion=cancelled commit=28d15711e70c71caada6185ebacf01a73d770815",
    "Fix workflow 'System3 GitHub Render Failure Tracker' run 30007446466 conclusion=failure commit=68e57caf7fb93da632626113bc7a8cccf0f527b2",
    "Fix workflow 'System3 Safe Repair Runner' run 30007073427 conclusion=cancelled commit=d6664adecaa52fb28271a8054603301f2d7aaab9",
    "Fix workflow 'System3 Experimental Solution Planner' run 30006956073 conclusion=failure commit=35c0d2d36aa5c588fa8ded0b21c306ee90f2e6f7",
    "Fix workflow 'System3 Safe Repair Runner' run 30006956035 conclusion=cancelled commit=35c0d2d36aa5c588fa8ded0b21c306ee90f2e6f7",
    "Fix workflow 'System3 Experimental Solution Planner' run 30006915603 conclusion=failure commit=cc5f4116a0a7aed36ae74e28d82dd94ea85e148d",
    "Fix workflow 'System3 Autopilot Proof Board' run 30006915483 conclusion=failure commit=cc5f4116a0a7aed36ae74e28d82dd94ea85e148d",
    "Fix workflow 'System3 Secure Install Credential Audit' run 30006915380 conclusion=failure commit=cc5f4116a0a7aed36ae74e28d82dd94ea85e148d",
    "Fix workflow 'System3 Autopilot Proof Board' run 30006912315 conclusion=failure commit=cc5f4116a0a7aed36ae74e28d82dd94ea85e148d",
    "Fix workflow 'System3 Experimental Solution Planner' run 30006896468 conclusion=failure commit=75325f8f2b0cd49b53c6bf882ad43793f60360fc",
    "Fix workflow 'System3 Safe Repair Runner' run 30006896391 conclusion=cancelled commit=75325f8f2b0cd49b53c6bf882ad43793f60360fc",
    "Fix workflow 'Dashboard Visible Issue Tracker' run 30006896363 conclusion=failure commit=75325f8f2b0cd49b53c6bf882ad43793f60360fc",
    "Fix workflow 'Dashboard Shell Diagnostic' run 30006889662 conclusion=failure commit=75325f8f2b0cd49b53c6bf882ad43793f60360fc",
    "Fix workflow 'System3 Safe Repair Runner' run 30006889556 conclusion=cancelled commit=75325f8f2b0cd49b53c6bf882ad43793f60360fc",
    "Fix workflow 'System3 Autopilot Proof Board' run 30006889547 conclusion=failure commit=75325f8f2b0cd49b53c6bf882ad43793f60360fc",
    "Fix workflow 'System3 Secure Install Credential Audit' run 30006889539 conclusion=failure commit=75325f8f2b0cd49b53c6bf882ad43793f60360fc",
    "Fix workflow 'Dashboard Visual Proof Strict Gate' run 30006889538 conclusion=failure commit=75325f8f2b0cd49b53c6bf882ad43793f60360fc",
    "Fix workflow 'Dashboard Visual Loading Postflight' run 30006889536 conclusion=failure commit=75325f8f2b0cd49b53c6bf882ad43793f60360fc"
  ]
}