{
  "failed_count": 40,
  "failed_runs": [
    {
      "branch": "main",
      "commit": "35fa3f5e3042ef66f2b1d2489a75f02643dd3e8c",
      "conclusion": "failure",
      "created_at": "2026-07-18T06:02:44Z",
      "html_url": "https://github.com/psw2025-cmd/Genesis_System3/actions/runs/29633312474",
      "run_id": 29633312474,
      "updated_at": "2026-07-18T06:11:17Z",
      "workflow": "System3 Safe Repair Runner"
    },
    {
      "branch": "main",
      "commit": "35fa3f5e3042ef66f2b1d2489a75f02643dd3e8c",
      "conclusion": "failure",
      "created_at": "2026-07-18T06:02:44Z",
      "html_url": "https://github.com/psw2025-cmd/Genesis_System3/actions/runs/29633312460",
      "run_id": 29633312460,
      "updated_at": "2026-07-18T06:02:54Z",
      "workflow": "System3 Experimental Solution Planner"
    },
    {
      "branch": "main",
      "commit": "35fa3f5e3042ef66f2b1d2489a75f02643dd3e8c",
      "conclusion": "failure",
      "created_at": "2026-07-18T06:02:39Z",
      "html_url": "https://github.com/psw2025-cmd/Genesis_System3/actions/runs/29633309872",
      "run_id": 29633309872,
      "updated_at": "2026-07-18T06:02:48Z",
      "workflow": "System3 Experimental Solution Planner"
    },
    {
      "branch": "main",
      "commit": "35fa3f5e3042ef66f2b1d2489a75f02643dd3e8c",
      "conclusion": "failure",
      "created_at": "2026-07-18T06:02:39Z",
      "html_url": "https://github.com/psw2025-cmd/Genesis_System3/actions/runs/29633309849",
      "run_id": 29633309849,
      "updated_at": "2026-07-18T06:05:57Z",
      "workflow": "Dashboard Shell Diagnostic"
    },
    {
      "branch": "main",
      "commit": "35fa3f5e3042ef66f2b1d2489a75f02643dd3e8c",
      "conclusion": "failure",
      "created_at": "2026-07-18T06:02:39Z",
      "html_url": "https://github.com/psw2025-cmd/Genesis_System3/actions/runs/29633309848",
      "run_id": 29633309848,
      "updated_at": "2026-07-18T06:02:46Z",
      "workflow": "Dashboard Visual Proof Strict Gate"
    },
    {
      "branch": "main",
      "commit": "35fa3f5e3042ef66f2b1d2489a75f02643dd3e8c",
      "conclusion": "cancelled",
      "created_at": "2026-07-18T06:02:39Z",
      "html_url": "https://github.com/psw2025-cmd/Genesis_System3/actions/runs/29633309846",
      "run_id": 29633309846,
      "updated_at": "2026-07-18T06:02:45Z",
      "workflow": "System3 Safe Repair Runner"
    },
    {
      "branch": "main",
      "commit": "35fa3f5e3042ef66f2b1d2489a75f02643dd3e8c",
      "conclusion": "failure",
      "created_at": "2026-07-18T06:02:39Z",
      "html_url": "https://github.com/psw2025-cmd/Genesis_System3/actions/runs/29633309838",
      "run_id": 29633309838,
      "updated_at": "2026-07-18T06:03:03Z",
      "workflow": "System3 Secure Install Credential Audit"
    },
    {
      "branch": "main",
      "commit": "35fa3f5e3042ef66f2b1d2489a75f02643dd3e8c",
      "conclusion": "failure",
      "created_at": "2026-07-18T06:02:39Z",
      "html_url": "https://github.com/psw2025-cmd/Genesis_System3/actions/runs/29633309817",
      "run_id": 29633309817,
      "updated_at": "2026-07-18T06:02:47Z",
      "workflow": "Dashboard Visual Loading Postflight"
    },
    {
      "branch": "main",
      "commit": "35fa3f5e3042ef66f2b1d2489a75f02643dd3e8c",
      "conclusion": "cancelled",
      "created_at": "2026-07-18T06:02:36Z",
      "html_url": "https://github.com/psw2025-cmd/Genesis_System3/actions/runs/29633308547",
      "run_id": 29633308547,
      "updated_at": "2026-07-18T06:02:40Z",
      "workflow": "System3 Safe Repair Runner"
    },
    {
      "branch": "main",
      "commit": "35fa3f5e3042ef66f2b1d2489a75f02643dd3e8c",
      "conclusion": "failure",
      "created_at": "2026-07-18T06:02:36Z",
      "html_url": "https://github.com/psw2025-cmd/Genesis_System3/actions/runs/29633308545",
      "run_id": 29633308545,
      "updated_at": "2026-07-18T06:02:49Z",
      "workflow": "System3 Experimental Solution Planner"
    },
    {
      "branch": "main",
      "commit": "35fa3f5e3042ef66f2b1d2489a75f02643dd3e8c",
      "conclusion": "cancelled",
      "created_at": "2026-07-18T06:02:36Z",
      "html_url": "https://github.com/psw2025-cmd/Genesis_System3/actions/runs/29633308539",
      "run_id": 29633308539,
      "updated_at": "2026-07-18T06:02:45Z",
      "workflow": "Dashboard Visible Issue Tracker"
    },
    {
      "branch": "main",
      "commit": "f9f9f122cb89109cb7e0a7fac2d6651ba0e76899",
      "conclusion": "cancelled",
      "created_at": "2026-07-18T06:02:17Z",
      "html_url": "https://github.com/psw2025-cmd/Genesis_System3/actions/runs/29633299214",
      "run_id": 29633299214,
      "updated_at": "2026-07-18T06:02:37Z",
      "workflow": "Dashboard Visible Issue Tracker"
    },
    {
      "branch": "main",
      "commit": "f9f9f122cb89109cb7e0a7fac2d6651ba0e76899",
      "conclusion": "cancelled",
      "created_at": "2026-07-18T06:02:17Z",
      "html_url": "https://github.com/psw2025-cmd/Genesis_System3/actions/runs/29633299209",
      "run_id": 29633299209,
      "updated_at": "2026-07-18T06:02:37Z",
      "workflow": "System3 Safe Repair Runner"
    },
    {
      "branch": "main",
      "commit": "f9f9f122cb89109cb7e0a7fac2d6651ba0e76899",
      "conclusion": "failure",
      "created_at": "2026-07-18T06:02:17Z",
      "html_url": "https://github.com/psw2025-cmd/Genesis_System3/actions/runs/29633299206",
      "run_id": 29633299206,
      "updated_at": "2026-07-18T06:02:27Z",
      "workflow": "System3 Experimental Solution Planner"
    },
    {
      "branch": "main",
      "commit": "f9f9f122cb89109cb7e0a7fac2d6651ba0e76899",
      "conclusion": "failure",
      "created_at": "2026-07-18T06:02:16Z",
      "html_url": "https://github.com/psw2025-cmd/Genesis_System3/actions/runs/29633298893",
      "run_id": 29633298893,
      "updated_at": "2026-07-18T06:03:05Z",
      "workflow": "Dashboard Visible Proof Warmed"
    },
    {
      "branch": "main",
      "commit": "f9f9f122cb89109cb7e0a7fac2d6651ba0e76899",
      "conclusion": "failure",
      "created_at": "2026-07-18T06:02:05Z",
      "html_url": "https://github.com/psw2025-cmd/Genesis_System3/actions/runs/29633292431",
      "run_id": 29633292431,
      "updated_at": "2026-07-18T06:03:13Z",
      "workflow": "System3 Autopilot Proof Board"
    },
    {
      "branch": "main",
      "commit": "d4f3d4e22dddb57fa9ea4c07719682b587d51115",
      "conclusion": "failure",
      "created_at": "2026-07-18T06:01:38Z",
      "html_url": "https://github.com/psw2025-cmd/Genesis_System3/actions/runs/29633278332",
      "run_id": 29633278332,
      "updated_at": "2026-07-18T06:02:34Z",
      "workflow": "System3 Autopilot Proof Board"
    },
    {
      "branch": "main",
      "commit": "d4f3d4e22dddb57fa9ea4c07719682b587d51115",
      "conclusion": "failure",
      "created_at": "2026-07-18T06:01:38Z",
      "html_url": "https://github.com/psw2025-cmd/Genesis_System3/actions/runs/29633278331",
      "run_id": 29633278331,
      "updated_at": "2026-07-18T06:01:50Z",
      "workflow": "System3 Experimental Solution Planner"
    },
    {
      "branch": "main",
      "commit": "d4f3d4e22dddb57fa9ea4c07719682b587d51115",
      "conclusion": "failure",
      "created_at": "2026-07-18T06:01:38Z",
      "html_url": "https://github.com/psw2025-cmd/Genesis_System3/actions/runs/29633278326",
      "run_id": 29633278326,
      "updated_at": "2026-07-18T06:02:03Z",
      "workflow": "System3 Secure Install Credential Audit"
    },
    {
      "branch": "main",
      "commit": "e57826a136b59bf566eb32f8e0b291f31b190054",
      "conclusion": "failure",
      "created_at": "2026-07-18T06:01:33Z",
      "html_url": "https://github.com/psw2025-cmd/Genesis_System3/actions/runs/29633276217",
      "run_id": 29633276217,
      "updated_at": "2026-07-18T06:02:42Z",
      "workflow": "System3 Autopilot Proof Board"
    },
    {
      "branch": "main",
      "commit": "ac17d0ed718b39019a432525721d223cce910095",
      "conclusion": "failure",
      "created_at": "2026-07-18T06:01:14Z",
      "html_url": "https://github.com/psw2025-cmd/Genesis_System3/actions/runs/29633268096",
      "run_id": 29633268096,
      "updated_at": "2026-07-18T06:01:25Z",
      "workflow": "Dashboard Visual Loading Postflight"
    },
    {
      "branch": "main",
      "commit": "ac17d0ed718b39019a432525721d223cce910095",
      "conclusion": "failure",
      "created_at": "2026-07-18T06:01:14Z",
      "html_url": "https://github.com/psw2025-cmd/Genesis_System3/actions/runs/29633268087",
      "run_id": 29633268087,
      "updated_at": "2026-07-18T06:02:15Z",
      "workflow": "System3 Autopilot Proof Board"
    },
    {
      "branch": "main",
      "commit": "ac17d0ed718b39019a432525721d223cce910095",
      "conclusion": "failure",
      "created_at": "2026-07-18T06:01:14Z",
      "html_url": "https://github.com/psw2025-cmd/Genesis_System3/actions/runs/29633268085",
      "run_id": 29633268085,
      "updated_at": "2026-07-18T06:01:24Z",
      "workflow": "Dashboard Visual Proof Strict Gate"
    },
    {
      "branch": "main",
      "commit": "ac17d0ed718b39019a432525721d223cce910095",
      "conclusion": "failure",
      "created_at": "2026-07-18T06:01:14Z",
      "html_url": "https://github.com/psw2025-cmd/Genesis_System3/actions/runs/29633268084",
      "run_id": 29633268084,
      "updated_at": "2026-07-18T06:01:24Z",
      "workflow": "System3 Experimental Solution Planner"
    },
    {
      "branch": "main",
      "commit": "ac17d0ed718b39019a432525721d223cce910095",
      "conclusion": "cancelled",
      "created_at": "2026-07-18T06:01:14Z",
      "html_url": "https://github.com/psw2025-cmd/Genesis_System3/actions/runs/29633268082",
      "run_id": 29633268082,
      "updated_at": "2026-07-18T06:02:50Z",
      "workflow": "System3 Safe Repair Runner"
    },
    {
      "branch": "main",
      "commit": "ac17d0ed718b39019a432525721d223cce910095",
      "conclusion": "cancelled",
      "created_at": "2026-07-18T06:01:14Z",
      "html_url": "https://github.com/psw2025-cmd/Genesis_System3/actions/runs/29633268079",
      "run_id": 29633268079,
      "updated_at": "2026-07-18T06:02:55Z",
      "workflow": "Dashboard Shell Diagnostic"
    },
    {
      "branch": "main",
      "commit": "ac17d0ed718b39019a432525721d223cce910095",
      "conclusion": "failure",
      "created_at": "2026-07-18T06:01:14Z",
      "html_url": "https://github.com/psw2025-cmd/Genesis_System3/actions/runs/29633268063",
      "run_id": 29633268063,
      "updated_at": "2026-07-18T06:01:31Z",
      "workflow": "System3 Secure Install Credential Audit"
    },
    {
      "branch": "main",
      "commit": "ac17d0ed718b39019a432525721d223cce910095",
      "conclusion": "failure",
      "created_at": "2026-07-18T06:00:18Z",
      "html_url": "https://github.com/psw2025-cmd/Genesis_System3/actions/runs/29633235502",
      "run_id": 29633235502,
      "updated_at": "2026-07-18T06:00:42Z",
      "workflow": "System3 Backend Live Simulation Proof"
    },
    {
      "branch": "main",
      "commit": "1014075e56bf2733ccec6515ffbd1992227d9883",
      "conclusion": "failure",
      "created_at": "2026-07-18T05:56:47Z",
      "html_url": "https://github.com/psw2025-cmd/Genesis_System3/actions/runs/29633133498",
      "run_id": 29633133498,
      "updated_at": "2026-07-18T05:57:12Z",
      "workflow": "Dashboard Deploy Provenance Gate"
    },
    {
      "branch": "main",
      "commit": "81de96be021e6dbe708ae0455851e9834d371efd",
      "conclusion": "failure",
      "created_at": "2026-07-18T05:50:19Z",
      "html_url": "https://github.com/psw2025-cmd/Genesis_System3/actions/runs/29632943679",
      "run_id": 29632943679,
      "updated_at": "2026-07-18T05:50:29Z",
      "workflow": "Dashboard Visual Proof Strict Gate"
    },
    {
      "branch": "main",
      "commit": "81de96be021e6dbe708ae0455851e9834d371efd",
      "conclusion": "failure",
      "created_at": "2026-07-18T05:50:19Z",
      "html_url": "https://github.com/psw2025-cmd/Genesis_System3/actions/runs/29632943640",
      "run_id": 29632943640,
      "updated_at": "2026-07-18T05:58:53Z",
      "workflow": "System3 Safe Repair Runner"
    },
    {
      "branch": "main",
      "commit": "81de96be021e6dbe708ae0455851e9834d371efd",
      "conclusion": "failure",
      "created_at": "2026-07-18T05:50:18Z",
      "html_url": "https://github.com/psw2025-cmd/Genesis_System3/actions/runs/29632943628",
      "run_id": 29632943628,
      "updated_at": "2026-07-18T05:50:28Z",
      "workflow": "System3 Experimental Solution Planner"
    },
    {
      "branch": "main",
      "commit": "81de96be021e6dbe708ae0455851e9834d371efd",
      "conclusion": "failure",
      "created_at": "2026-07-18T05:50:18Z",
      "html_url": "https://github.com/psw2025-cmd/Genesis_System3/actions/runs/29632943623",
      "run_id": 29632943623,
      "updated_at": "2026-07-18T05:50:41Z",
      "workflow": "System3 Secure Install Credential Audit"
    },
    {
      "branch": "main",
      "commit": "81de96be021e6dbe708ae0455851e9834d371efd",
      "conclusion": "failure",
      "created_at": "2026-07-18T05:50:18Z",
      "html_url": "https://github.com/psw2025-cmd/Genesis_System3/actions/runs/29632943622",
      "run_id": 29632943622,
      "updated_at": "2026-07-18T05:50:28Z",
      "workflow": "Dashboard Visual Loading Postflight"
    },
    {
      "branch": "main",
      "commit": "81de96be021e6dbe708ae0455851e9834d371efd",
      "conclusion": "failure",
      "created_at": "2026-07-18T05:50:18Z",
      "html_url": "https://github.com/psw2025-cmd/Genesis_System3/actions/runs/29632943620",
      "run_id": 29632943620,
      "updated_at": "2026-07-18T05:53:23Z",
      "workflow": "Dashboard Shell Diagnostic"
    },
    {
      "branch": "main",
      "commit": "81de96be021e6dbe708ae0455851e9834d371efd",
      "conclusion": "failure",
      "created_at": "2026-07-18T05:50:16Z",
      "html_url": "https://github.com/psw2025-cmd/Genesis_System3/actions/runs/29632942350",
      "run_id": 29632942350,
      "updated_at": "2026-07-18T06:13:16Z",
      "workflow": "Dashboard Visible Issue Tracker"
    },
    {
      "branch": "main",
      "commit": "81de96be021e6dbe708ae0455851e9834d371efd",
      "conclusion": "failure",
      "created_at": "2026-07-18T05:50:16Z",
      "html_url": "https://github.com/psw2025-cmd/Genesis_System3/actions/runs/29632942347",
      "run_id": 29632942347,
      "updated_at": "2026-07-18T05:50:25Z",
      "workflow": "System3 Experimental Solution Planner"
    },
    {
      "branch": "main",
      "commit": "81de96be021e6dbe708ae0455851e9834d371efd",
      "conclusion": "cancelled",
      "created_at": "2026-07-18T05:50:16Z",
      "html_url": "https://github.com/psw2025-cmd/Genesis_System3/actions/runs/29632942325",
      "run_id": 29632942325,
      "updated_at": "2026-07-18T05:50:20Z",
      "workflow": "System3 Safe Repair Runner"
    },
    {
      "branch": "main",
      "commit": "cd00c2b54094e23c799955f25d989a6e1d0b3aab",
      "conclusion": "cancelled",
      "created_at": "2026-07-18T05:49:44Z",
      "html_url": "https://github.com/psw2025-cmd/Genesis_System3/actions/runs/29632928011",
      "run_id": 29632928011,
      "updated_at": "2026-07-18T05:50:17Z",
      "workflow": "Dashboard Visible Issue Tracker"
    },
    {
      "branch": "main",
      "commit": "cd00c2b54094e23c799955f25d989a6e1d0b3aab",
      "conclusion": "cancelled",
      "created_at": "2026-07-18T05:49:44Z",
      "html_url": "https://github.com/psw2025-cmd/Genesis_System3/actions/runs/29632928004",
      "run_id": 29632928004,
      "updated_at": "2026-07-18T05:50:31Z",
      "workflow": "System3 Safe Repair Runner"
    }
  ],
  "generated_utc": "2026-07-18T06:13:34.581586+00:00",
  "note": "Workflow failure tracker. Failed workflows remain TODO until a later successful run is proven.",
  "repository": "psw2025-cmd/Genesis_System3",
  "status": "BLOCKED",
  "todo": [
    "Fix workflow 'System3 Safe Repair Runner' run 29633312474 conclusion=failure commit=35fa3f5e3042ef66f2b1d2489a75f02643dd3e8c",
    "Fix workflow 'System3 Experimental Solution Planner' run 29633312460 conclusion=failure commit=35fa3f5e3042ef66f2b1d2489a75f02643dd3e8c",
    "Fix workflow 'System3 Experimental Solution Planner' run 29633309872 conclusion=failure commit=35fa3f5e3042ef66f2b1d2489a75f02643dd3e8c",
    "Fix workflow 'Dashboard Shell Diagnostic' run 29633309849 conclusion=failure commit=35fa3f5e3042ef66f2b1d2489a75f02643dd3e8c",
    "Fix workflow 'Dashboard Visual Proof Strict Gate' run 29633309848 conclusion=failure commit=35fa3f5e3042ef66f2b1d2489a75f02643dd3e8c",
    "Fix workflow 'System3 Safe Repair Runner' run 29633309846 conclusion=cancelled commit=35fa3f5e3042ef66f2b1d2489a75f02643dd3e8c",
    "Fix workflow 'System3 Secure Install Credential Audit' run 29633309838 conclusion=failure commit=35fa3f5e3042ef66f2b1d2489a75f02643dd3e8c",
    "Fix workflow 'Dashboard Visual Loading Postflight' run 29633309817 conclusion=failure commit=35fa3f5e3042ef66f2b1d2489a75f02643dd3e8c",
    "Fix workflow 'System3 Safe Repair Runner' run 29633308547 conclusion=cancelled commit=35fa3f5e3042ef66f2b1d2489a75f02643dd3e8c",
    "Fix workflow 'System3 Experimental Solution Planner' run 29633308545 conclusion=failure commit=35fa3f5e3042ef66f2b1d2489a75f02643dd3e8c",
    "Fix workflow 'Dashboard Visible Issue Tracker' run 29633308539 conclusion=cancelled commit=35fa3f5e3042ef66f2b1d2489a75f02643dd3e8c",
    "Fix workflow 'Dashboard Visible Issue Tracker' run 29633299214 conclusion=cancelled commit=f9f9f122cb89109cb7e0a7fac2d6651ba0e76899",
    "Fix workflow 'System3 Safe Repair Runner' run 29633299209 conclusion=cancelled commit=f9f9f122cb89109cb7e0a7fac2d6651ba0e76899",
    "Fix workflow 'System3 Experimental Solution Planner' run 29633299206 conclusion=failure commit=f9f9f122cb89109cb7e0a7fac2d6651ba0e76899",
    "Fix workflow 'Dashboard Visible Proof Warmed' run 29633298893 conclusion=failure commit=f9f9f122cb89109cb7e0a7fac2d6651ba0e76899",
    "Fix workflow 'System3 Autopilot Proof Board' run 29633292431 conclusion=failure commit=f9f9f122cb89109cb7e0a7fac2d6651ba0e76899",
    "Fix workflow 'System3 Autopilot Proof Board' run 29633278332 conclusion=failure commit=d4f3d4e22dddb57fa9ea4c07719682b587d51115",
    "Fix workflow 'System3 Experimental Solution Planner' run 29633278331 conclusion=failure commit=d4f3d4e22dddb57fa9ea4c07719682b587d51115",
    "Fix workflow 'System3 Secure Install Credential Audit' run 29633278326 conclusion=failure commit=d4f3d4e22dddb57fa9ea4c07719682b587d51115",
    "Fix workflow 'System3 Autopilot Proof Board' run 29633276217 conclusion=failure commit=e57826a136b59bf566eb32f8e0b291f31b190054",
    "Fix workflow 'Dashboard Visual Loading Postflight' run 29633268096 conclusion=failure commit=ac17d0ed718b39019a432525721d223cce910095",
    "Fix workflow 'System3 Autopilot Proof Board' run 29633268087 conclusion=failure commit=ac17d0ed718b39019a432525721d223cce910095",
    "Fix workflow 'Dashboard Visual Proof Strict Gate' run 29633268085 conclusion=failure commit=ac17d0ed718b39019a432525721d223cce910095",
    "Fix workflow 'System3 Experimental Solution Planner' run 29633268084 conclusion=failure commit=ac17d0ed718b39019a432525721d223cce910095",
    "Fix workflow 'System3 Safe Repair Runner' run 29633268082 conclusion=cancelled commit=ac17d0ed718b39019a432525721d223cce910095",
    "Fix workflow 'Dashboard Shell Diagnostic' run 29633268079 conclusion=cancelled commit=ac17d0ed718b39019a432525721d223cce910095",
    "Fix workflow 'System3 Secure Install Credential Audit' run 29633268063 conclusion=failure commit=ac17d0ed718b39019a432525721d223cce910095",
    "Fix workflow 'System3 Backend Live Simulation Proof' run 29633235502 conclusion=failure commit=ac17d0ed718b39019a432525721d223cce910095",
    "Fix workflow 'Dashboard Deploy Provenance Gate' run 29633133498 conclusion=failure commit=1014075e56bf2733ccec6515ffbd1992227d9883",
    "Fix workflow 'Dashboard Visual Proof Strict Gate' run 29632943679 conclusion=failure commit=81de96be021e6dbe708ae0455851e9834d371efd",
    "Fix workflow 'System3 Safe Repair Runner' run 29632943640 conclusion=failure commit=81de96be021e6dbe708ae0455851e9834d371efd",
    "Fix workflow 'System3 Experimental Solution Planner' run 29632943628 conclusion=failure commit=81de96be021e6dbe708ae0455851e9834d371efd",
    "Fix workflow 'System3 Secure Install Credential Audit' run 29632943623 conclusion=failure commit=81de96be021e6dbe708ae0455851e9834d371efd",
    "Fix workflow 'Dashboard Visual Loading Postflight' run 29632943622 conclusion=failure commit=81de96be021e6dbe708ae0455851e9834d371efd",
    "Fix workflow 'Dashboard Shell Diagnostic' run 29632943620 conclusion=failure commit=81de96be021e6dbe708ae0455851e9834d371efd",
    "Fix workflow 'Dashboard Visible Issue Tracker' run 29632942350 conclusion=failure commit=81de96be021e6dbe708ae0455851e9834d371efd",
    "Fix workflow 'System3 Experimental Solution Planner' run 29632942347 conclusion=failure commit=81de96be021e6dbe708ae0455851e9834d371efd",
    "Fix workflow 'System3 Safe Repair Runner' run 29632942325 conclusion=cancelled commit=81de96be021e6dbe708ae0455851e9834d371efd",
    "Fix workflow 'Dashboard Visible Issue Tracker' run 29632928011 conclusion=cancelled commit=cd00c2b54094e23c799955f25d989a6e1d0b3aab",
    "Fix workflow 'System3 Safe Repair Runner' run 29632928004 conclusion=cancelled commit=cd00c2b54094e23c799955f25d989a6e1d0b3aab"
  ]
}